ninja_service_objects/__init__.py
ninja_service_objects/apps.py
ninja_service_objects/fields.py
ninja_service_objects/services.py
django_ninja_service_objects-0.1.2.dist-info/METADATA
django_ninja_service_objects-0.1.2.dist-info/WHEEL
django_ninja_service_objects-0.1.2.dist-info/top_level.txt
django_ninja_service_objects-0.1.2.dist-info/RECORD
