Metadata-Version: 2.4
Name: django-ninja-service-objects
Version: 0.1.2
Summary: Service objects for Django Ninja using Pydantic validation
Author-email: Hans Ramírez <monkey@bekind.software>
License: MIT
Project-URL: Homepage, https://github.com/bekindsoft/ninja-service-objects
Project-URL: Documentation, https://github.com/bekindsoft/ninja-service-objects#readme
Project-URL: Repository, https://github.com/bekindsoft/ninja-service-objects
Project-URL: Issues, https://github.com/bekindsoft/ninja-service-objects/issues
Keywords: django,ninja,service-objects,pydantic,business-logic
Classifier: Development Status :: 3 - Alpha
Classifier: Environment :: Web Environment
Classifier: Framework :: Django
Classifier: Framework :: Django :: 4.1
Classifier: Framework :: Django :: 4.2
Classifier: Framework :: Django :: 5.0
Classifier: Intended Audience :: Developers
Classifier: License :: OSI Approved :: MIT License
Classifier: Operating System :: OS Independent
Classifier: Programming Language :: Python :: 3
Classifier: Programming Language :: Python :: 3.10
Classifier: Programming Language :: Python :: 3.11
Classifier: Programming Language :: Python :: 3.12
Classifier: Topic :: Internet :: WWW/HTTP
Classifier: Topic :: Software Development :: Libraries :: Python Modules
Requires-Python: >=3.10
Requires-Dist: django>=4.0
Requires-Dist: django-ninja>=1.0
Requires-Dist: pydantic>=2.0
Provides-Extra: dev
Requires-Dist: pytest>=7.0; extra == "dev"
Requires-Dist: pytest-django>=4.5; extra == "dev"
Requires-Dist: ruff>=0.8.0; extra == "dev"
Requires-Dist: mypy>=1.0; extra == "dev"
